power_grid_model_ds/__init__.py
power_grid_model_ds/arrays.py
power_grid_model_ds/constants.py
power_grid_model_ds/enums.py
power_grid_model_ds/errors.py
power_grid_model_ds/fancypy.py
power_grid_model_ds/generators.py
power_grid_model_ds/graph_models.py
power_grid_model_ds/visualizer.py
power_grid_model_ds/_core/__init__.py
power_grid_model_ds/_core/fancypy.py
power_grid_model_ds/_core/power_grid_model_interface.py
power_grid_model_ds/_core/data_source/__init__.py
power_grid_model_ds/_core/data_source/generator/__init__.py
power_grid_model_ds/_core/data_source/generator/grid_generators.py
power_grid_model_ds/_core/data_source/generator/arrays/__init__.py
power_grid_model_ds/_core/data_source/generator/arrays/base.py
power_grid_model_ds/_core/data_source/generator/arrays/line.py
power_grid_model_ds/_core/data_source/generator/arrays/node.py
power_grid_model_ds/_core/data_source/generator/arrays/source.py
power_grid_model_ds/_core/data_source/generator/arrays/transformer.py
power_grid_model_ds/_core/model/__init__.py
power_grid_model_ds/_core/model/constants.py
power_grid_model_ds/_core/model/arrays/__init__.py
power_grid_model_ds/_core/model/arrays/pgm_arrays.py
power_grid_model_ds/_core/model/arrays/base/__init__.py
power_grid_model_ds/_core/model/arrays/base/_build.py
power_grid_model_ds/_core/model/arrays/base/_filters.py
power_grid_model_ds/_core/model/arrays/base/_modify.py
power_grid_model_ds/_core/model/arrays/base/_optional.py
power_grid_model_ds/_core/model/arrays/base/_string.py
power_grid_model_ds/_core/model/arrays/base/array.py
power_grid_model_ds/_core/model/arrays/base/errors.py
power_grid_model_ds/_core/model/containers/__init__.py
power_grid_model_ds/_core/model/containers/base.py
power_grid_model_ds/_core/model/containers/helpers.py
power_grid_model_ds/_core/model/dtypes/__init__.py
power_grid_model_ds/_core/model/dtypes/appliances.py
power_grid_model_ds/_core/model/dtypes/branches.py
power_grid_model_ds/_core/model/dtypes/id.py
power_grid_model_ds-1.6.1.dist-info/licenses/LICENSE
power_grid_model_ds-1.6.1.dist-info/METADATA
power_grid_model_ds-1.6.1.dist-info/WHEEL
power_grid_model_ds-1.6.1.dist-info/top_level.txt
power_grid_model_ds-1.6.1.dist-info/RECORD
