Metadata-Version: 2.4
Name: power-grid-model-ds
Version: 1.6.1
Summary: Power Grid Model extension which provides a grid data structure for simulation and analysis
Author-email: Contributors to the Power Grid Model project <powergridmodel@lfenergy.org>
License: MPL-2.0
Project-URL: Home-page, https://lfenergy.org/projects/power-grid-model/
Project-URL: GitHub, https://github.com/PowerGridModel/power-grid-model-ds
Project-URL: Documentation, https://power-grid-model-ds.readthedocs.io/en/stable/
Project-URL: Mailing-list, https://lists.lfenergy.org/g/powergridmodel
Project-URL: Discussion, https://github.com/orgs/PowerGridModel/discussions
Keywords: power grid model
Classifier: Programming Language :: Python :: 3
Classifier: Intended Audience :: Developers
Classifier: Intended Audience :: Science/Research
Classifier: License :: OSI Approved :: Mozilla Public License 2.0 (MPL 2.0)
Classifier: Operating System :: Microsoft :: Windows
Classifier: Operating System :: POSIX :: Linux
Classifier: Operating System :: MacOS
Classifier: Topic :: Scientific/Engineering :: Physics
Requires-Python: >=3.12
License-File: LICENSE
Requires-Dist: power-grid-model>=1.12.11
Requires-Dist: rustworkx>=0.15.1
Requires-Dist: numpy>=2.0
Provides-Extra: visualizer
Requires-Dist: dash>=3.0.0; extra == "visualizer"
Requires-Dist: dash-bootstrap-components>=2.0.0; extra == "visualizer"
Requires-Dist: dash-cytoscape>=1.0.2; extra == "visualizer"
Provides-Extra: pandas
Requires-Dist: pandas>=2.2.1; extra == "pandas"
Dynamic: license-file
